{
  "Typer": [
    {
      "name": "Rødvin",
      "svg": "/mock-path/red-wine.svg"
    },
    {
      "name": "Hvidvin",
      "svg": "/mock-path/white-wine.svg"
    },
    {
      "name": "Rosé",
      "svg": "/mock-path/rose-wine.svg"
    },
    {
      "name": "Mousserende",
      "svg": "/mock-path/sparkling-wine.svg"
    }
  ],
  "Alle vine": {
    "name": "Alle vine",
    "svg": "/mock-path/all-wine.svg"
  },
  "Område": ["Frankrig", "Slovenien", "Portugal", "Spanien", "Italien", "Østrig", "Ungarn", "Tyskland", "Danmark", "Australien", "Georgien", "Tjekkiet", "Grækenland", "New Zealand", "Slovakiet", "Argentina", "Kroatien", "Bulgarien", "Sydafrika", "Sverige"],
  "Gå på opdagelse": ["Billigjuice (som stadig er psyko!)", "Weird shit (på den gode måde!)", "Psykovin!"]
}
